README.rst
setup.py
vturra/__init__.py
vturra/asys.py
vturra/rra.py
vturra.egg-info/PKG-INFO
vturra.egg-info/SOURCES.txt
vturra.egg-info/dependency_links.txt
vturra.egg-info/entry_points.txt
vturra.egg-info/requires.txt
vturra.egg-info/top_level.txt