Metadata-Version: 1.1
Name: vturra
Version: v1.0
Summary: Downloads results from VTU website and analyzes the result
Home-page: UNKNOWN
Author: Muhammed Thaha
Author-email: mthaha1989@gmail.com
License: Apache Software License
Download-URL: https://github.com/stormvirux/vturra
Platform: any
Classifier: Programming Language :: Python
Classifier: Development Status :: 5 - Production/Stable
Classifier: Natural Language :: English
Classifier: Environment :: Console
Classifier: Intended Audience :: Developers
Classifier: License :: OSI Approved :: MIT License
Classifier: Operating System :: OS Independent
Classifier: Topic :: Scientific/Engineering :: Information Analysis
